odoo10_addon_l10n_br_crm-10.0.1.0.0.99.dev13-nspkg.pth
odoo/addons/l10n_br_crm/README.rst
odoo/addons/l10n_br_crm/__init__.py
odoo/addons/l10n_br_crm/__manifest__.py
odoo/addons/l10n_br_crm/i18n/l10n_br_crm.pot
odoo/addons/l10n_br_crm/models/__init__.py
odoo/addons/l10n_br_crm/models/crm_lead.py
odoo/addons/l10n_br_crm/static/description/icon.png
odoo/addons/l10n_br_crm/tests/__init__.py
odoo/addons/l10n_br_crm/tests/test_crm_lead.py
odoo/addons/l10n_br_crm/tests/test_crm_onchange.py
odoo/addons/l10n_br_crm/views/crm_lead_view.xml
odoo/addons/l10n_br_crm/views/crm_opportunity_view.xml
odoo10_addon_l10n_br_crm-10.0.1.0.0.99.dev13.dist-info/METADATA
odoo10_addon_l10n_br_crm-10.0.1.0.0.99.dev13.dist-info/WHEEL
odoo10_addon_l10n_br_crm-10.0.1.0.0.99.dev13.dist-info/namespace_packages.txt
odoo10_addon_l10n_br_crm-10.0.1.0.0.99.dev13.dist-info/top_level.txt
odoo10_addon_l10n_br_crm-10.0.1.0.0.99.dev13.dist-info/RECORD
